hepbasestack/__init__.py
hepbasestack/colors.py
hepbasestack/itools.py
hepbasestack/layout.py
hepbasestack/logger.py
hepbasestack/visual.py
hepbasestack-0.1.8.dist-info/LICENSE
hepbasestack-0.1.8.dist-info/METADATA
hepbasestack-0.1.8.dist-info/WHEEL
hepbasestack-0.1.8.dist-info/top_level.txt
hepbasestack-0.1.8.dist-info/RECORD
